[
  {
    "id": "p1",
    "name": "Mixed Bouquet",
    "slug": "mixed-bouquet",
    "price": 35,
    "compareAtPrice": 45,
    "description": "Beautiful mixed arrangement with seasonal flowers and greenery",
    "tags": ["birthday", "anniversary"],
    "image": "/images/mixed-bouquet.png",
    "featured": true,
    "stock": 8,
    "type": "Mixed",
    "condition": "Fresh & New",
    "care": "Cool water daily",
    "rating": { "average": 4.8, "counts": { "5": 2, "4": 1, "3": 0 } }
  },
  {
    "id": "p2",
    "name": "Pink Peonies",
    "slug": "pink-peonies",
    "price": 40,
    "compareAtPrice": 50,
    "description": "Luxurious pink peonies for special occasions and celebrations",
    "tags": ["seasonal", "wedding"],
    "image": "/images/pink-peonies.png",
    "featured": true,
    "stock": 12,
    "type": "Peonies",
    "condition": "Fresh & New",
    "care": "Change water daily",
    "rating": { "average": 4.7, "counts": { "5": 2, "4": 1, "3": 0 } }
  },
  {
    "id": "p3",
    "name": "Pink Roses",
    "slug": "pink-roses",
    "price": 30,
    "description": "Soft pink roses expressing gratitude and appreciation",
    "tags": ["birthday"],
    "image": "/images/pink-roses.png",
    "stock": 5,
    "type": "Roses",
    "condition": "Fresh",
    "care": "Trim stems at an angle",
    "rating": { "average": 4.5, "counts": { "5": 1, "4": 1 } }
  }
]
